flet_datatable2/__init__.py
flet_datatable2/datacolumn2.py
flet_datatable2/datarow2.py
flet_datatable2/datatable2.py
flet_datatable2-0.80.5.dist-info/licenses/LICENSE
flutter/flet_datatable2/pubspec.lock
flutter/flet_datatable2/pubspec.yaml
flutter/flet_datatable2/lib/flet_datatable2.dart
flutter/flet_datatable2/lib/src/data_sources.dart
flutter/flet_datatable2/lib/src/datatable2.dart
flutter/flet_datatable2/lib/src/extension.dart
flutter/flet_datatable2/lib/src/utils/datatable.dart
flet_datatable2-0.80.5.dist-info/METADATA
flet_datatable2-0.80.5.dist-info/WHEEL
flet_datatable2-0.80.5.dist-info/top_level.txt
flet_datatable2-0.80.5.dist-info/RECORD
